{"9BH288XfXPlKbJcWROQ35A==":"index.3-2000x998.jpg","AjFCC/jnVaWOkOYTywE2sw==":"index.3-2000x998.jpeg","R031y4n7pQl+9EkKc2tIyg==":"index.1-1944x2592.jpg","IYb+NCLFJ5K89CkpAx0Urg==":"index.2-684x456.jpg","F5yqK4zt3eaWkZzYbobSbA==":"01-l-1200x900.jpg","y98t8tGQxS8goy2fKif11Q==":"01-1024x738.jpg","PXTdD2NvTmhM9rBkDxTzRg==":"02-2000x884.jpg","8FkD5W/g3cIp9VGfMoOlGA==":"03-152x152.jpg","efFLuygGXJED5MXrwXbEig==":"room-laptop.jpeg","LEBnp2Fe4YNO2Z7tV3QVkQ==":"01-l-1200x900.jpeg","N8r5OzbwmQUGCLRaVXh/ng==":"01-437x240.jpg","uWr7dSdZKOWa6oGidjR+JA==":"img-1540-1600x1195.jpg","VCeCIrJ52XdYk/UTYp9bTw==":"img_20180521_101743-116-1066x1066.jpg","pExF4k2CqlwN/0LfpUM82w==":"img_20180602-90509-2000x2667.jpg","ueZypkxnstRPneXjZTK5Jw==":"img_20180606_085950-pano-2000x519.jpg","0muRlFAgnzKjNAPqwCVz8A==":"img_20190609_093918-effects-2000x1500.jpg","GckN0pa0IXmxUrwcu7Zf0g==":"img-20180418-wa0000-1600x1066.jpg","mNLOU/pPHT0qDMdzNBwkjw==":"img-20180418-wa0001-1600x1066.jpg","trUkWIymQi3js4Anttkuqg==":"img-20180418-wa0002-1600x1066.jpg","utP2rdKDvOOfY7/ecejObw==":"imgp0966-1600x798.jpg","x/RDhdKIyg4w6bGuXC+lqw==":"p2140004-1600x1200.jpg","sJy0ye676Y3RjDErzUqtnQ==":"room-1-1202x1600.jpg","KFm91S1Uj/cZ6ICjLhtv6g==":"room-1-1202x1600-800x1065.jpg","YhWdZ4trKZQMr6/LZ/59zw==":"06-152x132.jpg","vQXyognCEjCv3R1b3NsTCA==":"05-152x114.jpg","NyFwcHS872vZDXXuTcbKNA==":"02-152x143.jpg","poUA2KUykpQtMFJtjnIY1w==":"img_20181019-122017-600x450.jpg","Cb0A1g71swmZF8UUY9PYqQ==":"02-l-600x400.jpg","omdpwLHl7CZyiRWpgE7hcA==":"01-l-600x400.jpg","/j7wBGAmcG0iXauWqwjqyw==":"03-l-600x400.jpg","2LpWlL9I10oOncYbNHntjA==":"01-l-560x420.jpg","lV7LdlZwas8sPLokrL1j0Q==":"logo-627x48.png","pc/GlIrr/AksqBICzn1+JQ==":"bestprice-262x128.png","Y23RQQgkthv61snddQQGyw==":"bestprice-1-262x128.png","zFK7pfIYcl6r5olwHM2ydg==":"01-284x282.jpg","IE9wxpqz9t3r1OsQajjExg==":"03-l-1-600x400.jpg","kUPdFmJaJ+85xR63RmwnCg==":"04-04%20(2)-152x114.jpg","1Q0THKvuHTzj16lFuuHG8w==":"09-8-560x398.jpg","t9zTXiyNaOJE1XxxSbDpuQ==":"02-l-1-600x400.jpg","usyGFp6xbic/Y7cALNWngw==":"04-l-600x400.jpg","PJ5YqKqg2TdhR+Diy9MrFQ==":"photo449-600x263.jpg","tUeqIHegIGLju7GbbuEPiA==":"01-1024x738.jpeg","fq7miNASaGXx+IvEi4egAA==":"03%203-800x364.jpg","DbYNI2f+eT2FeHg710bHxw==":"05-800x600.jpg","mc+3lXPAwfzgSEJr5vTkWQ==":"07-640x426.jpg","PkuXLId82OphyAbzFPRJLg==":"image0-2000x1500.jpg","Rl0VenHI6i8PPQdzkKTvDw==":"10-1024x450.jpg","3/ueffumm6nkqD7YgDppEw==":"img_20181019-122017-600x450.jpeg","W7purULp5ZcLQP1u11IqGA==":"img_20181019-122018-600x450.jpeg","4grkfYGFOP0TOT35wpFg2w==":"img_20181019-122019-600x450.jpeg","CboqiN0O9DZxMfXYSkadPA==":"img_20181019-122020-600x450.jpeg","Az0s48LaKMnu6iO8xalAwA==":"img_20181019-122021-600x450.jpeg","oNxcSLunbTJY1jJeGej9oQ==":"562-oxwich4-600x400.jpg","6r3wQp90BvYFCW1dW+u0BQ==":"03-l-600x450.jpg","H5w8FaoysKEUC3PpCTiA3Q==":"475-things3-261x113.jpg","fI4ixjY37zzg4ODStcJZjg==":"475-things3-261x113.jpeg","UYDCS8hYbNiAtnd3GK3hCA==":"09-600x264.jpg","b8YCtaZPRcXrzhI6drNCRw==":"coasteering-600x234.jpg","g9VTLdyF2SLKFN4bChO4vg==":"coasteering-600x234.jpeg","Vly/2Vkgvp033t8urSBIdQ==":"758-04-l-600x480.jpg","ypIRB0cSIb++WAB7fJDg9g==":"paddle%20boarding-600x400.jpg","55/ilGSMpcR8tJnYDMVkPg==":"571-things15-594x392.jpg","iS9kXpNlvA6nKhI5IOSOAQ==":"07-600x399.jpg","3oz8sbINLexfo6pG1XyDdg==":"07-600x399.jpeg","G4UztTPiUfYu4zxOusOp2Q==":"snip%202020-05-22%2011.51.04-160x39.png","VKb/nM1mA/0Kq43xCiTp5Q==":"snip%202020-05-22%2011.51.04-160x39.png","qATzCHj5EJSHm1o6wg1znw==":"snip%202020-05-22%2011.51.04-433x105.png","oohp7bLqPTzUx+OlTzVIPA==":"snip%202020-05-22%2011.51.04-433x105.png","ddbxmb8cZjaZ8WuLb99qrg==":"snip%202020-05-22%2012.28.14-600x559.png","EC1UdNfdqqnf9v0zVelIhA==":"snip%202020-05-22%2012.35.31-600x496.png","VJP/wax1awXueSErw+eWdw==":"snip%202020-05-22%2012.42.31-600x370.png","XE04DCHMCM3IYiufDCczWg==":"snip%202020-05-22%2012.46.58-600x480.png","Sn99PQ0eJv+yI9Hjm4D+dw==":"ship-285x177.jpg","+JMyonwJQDHHFtM5vL5phQ==":"smugglers-285x177.jpg","Y07+WYOf+5X6v0O2j37VVw==":"king%20arthur-600x237.jpg","Govlo61Hq+XgW82D8HcCuA==":"britanniagower-474x355.jpg","L2iZjmyaH2eCwisVU9AvpA==":"britanniagower-474x355.jpeg","R+i62/6DGvSBH1jbuVhtBQ==":"beach%20house-600x398.jpg","iDC88fEQoTQLFGNbQoxfoA==":"the-bay-bistro-600x398.jpg","puLBr5YF5sPoslVpr1zAjw==":"seafaraer-275x183.jpg","oWBoZRs6sJvlWNEmICu/bw==":"captains%20table-550x310.jpg","if1TYTwWKWsYEWqg+h3gGg==":"captains%20table-550x310.jpeg","9M9yqRKOwLzZtIyC1aLW6w==":"king%20arthur-600x237.jpeg","e1LqALGdYFF5yok11M19WA==":"smugglers-285x177.jpeg","iYcT4msKbj28pczddi/p/A==":"king%20arthur-600x237.jpeg","Uyp8TkHgoObs/QP+iZfRCA==":"smugglers-1-285x177.jpeg","jM4pCnUhWOe5sVl2ER7RCw==":"king%20arthur-600x237.jpeg","Gh+m2WbAmvCp8pzO2ldvlw==":"britanniagower-1-474x355.jpeg","tHB+fVIEwFgrfD5s1K/zHw==":"britanniagower-2-474x355.jpeg","N4yXtdzOubsNqxEjgYdYeg==":"the-coffee-house-550x412.jpg","t28UbWCseo6Xc+TUoTut0g==":"the-coffee-house-550x412.jpeg","BvnPB4YQuCMIMtUS1F6UGw==":"s3-3-684x456.jpg","gNv0Xk0VF4ALreaj1XZ9zA==":"img-609-2000x1494.jpg","aKC3k8oR1sLOKmoHrueOiw==":"img-609-2000x1494.jpeg","ZjKWmTdHuKIFi7fmFfndOg==":"img-612-2000x1494.jpg","YK1f1JmC7Slzq4+tG4uWAA==":"img-605-2000x1494.jpg","ilN+0ChcQ15ryiGinW5wag==":"img-605-2000x1494.jpeg","xs1t1rt6Ys/K/3uw7lXwQg==":"01d-640x480.png","BRXEl+BJ92Ft8GK0GjwBVQ==":"06-800x600.jpg","S33qCopldHvb09EGWLpGzA==":"03-l-800x600.jpg","R0g5DcU4LBGkL6xRRHafBQ==":"562-oxwich4-800x533.jpg","m03ybkXJtahHmbS2nM+jvA==":"712-slide-3d-800x600.jpg","0D7tARm/FFUFei4R1Wtc5w==":"758-04-l-1-600x480.jpg","eP/VhNYBmSQpH79AXUZ/7A==":"826-photo14-800x600.jpg","RIGI0IxkPHweqG67/h5Kxw==":"758-04-l-1-600x480.jpeg","iVZLYcpZJtTWhwVBHZyHmw==":"758-04-l-2-600x480.jpeg","JqEjww8NVqsP8mBJ/cgsfQ==":"portfolio-23-640x480.jpg","eKd1iB/xGOa4NqaoV3xZyA==":"img_20180521_101743-116-1066x1066.jpeg","cv52s4Lnw9RQbQ+URF7Y/A==":"img_20180521_101743-117-1066x1066.jpeg","757q3gDGh967K+ZE0+YIQg==":"img-20180521-101743-116-1066x1066-800x800.jpg","2nbZJwyfUjAnkPuNUL98/w==":"01-1024x738-800x570.jpeg","oz6FYucfFumTOUmvTyXYig==":"03-3-800x364-800x364.jpg","Wz6e/a0i0p37aYsgEbYVDQ==":"portfolio-22-640x480.jpg","B8HPjkw1RFWlYR7LIPCKNg==":"832-photo429-800x600.jpg","ZMqWuDQxiPpzA4872HOjng==":"portfolio-10-640x480.jpg","iZ+JKPtU2MyrvJJ+JtfGtQ==":"gnd%20floor%20colour%20coded-2000x2888.jpg","LISCTYVasguT1TsVcTVfTQ==":"snip%202020-05-26%2010.50.43-600x387.png","CqNd6rgkw1xFzaqdmZ+xNA==":"oxwich%20bay-275x183.jpg","wvZVMiEXt1pF/varLy17/w==":"oxwixh%202-275x183.jpg","0erzOZtWzRBY7KlGlPvIIg==":"oxwixh%202-275x183.jpeg","9WrrqalZDhTvwptPpU7Lgw==":"wormshead-259x194.jpg","PaSgW32Koaxn4AV5TgD1VQ==":"06-l-560x415.jpg","x4C+K5rW7rEFXQnbCAY/9g==":"03-l-684x456.jpg","ymvPGmfFYrbuWRVcHjgsTQ==":"s3-2-456x684.jpg","r09JFlzl+A/fFC1gotfQgg==":"s3-5-684x456.jpg","fqUqk1VEf7G+0IdZWvDDnQ==":"suite%201c-1944x2592.jpg","Jp2umUABvRIEuhbc8orbAA==":"02-l-456x684.jpg"}